anycsv/__init__.py
anycsv/cli.py
anycsv/config.py
anycsv/config.yaml
anycsv/csv.py
anycsv/csv_model.py
anycsv/csv_parser.py
anycsv/dialect.py
anycsv/encoding.py
anycsv/exceptions.py
anycsv/io_tools.py
pyanycsv-0.7.1.dist-info/METADATA
pyanycsv-0.7.1.dist-info/RECORD
pyanycsv-0.7.1.dist-info/WHEEL
pyanycsv-0.7.1.dist-info/entry_points.txt
pyanycsv-0.7.1.dist-info/top_level.txt
