Metadata-Version: 2.1
Name: pyanycsv
Version: 0.7.1
Summary: A Python replacement for the standard csv library, including cchardet detection and URL reading
Home-page: https://github.com/jumbrich/pyanycsv
Author: jumbrich
Author-email: jueumb@gmail.com
License: mit
Platform: any
Classifier: Development Status :: 4 - Beta
Classifier: Programming Language :: Python
Requires-Dist: structlog
Requires-Dist: pyjuhelpers
Requires-Dist: click
